{"_path":"/apps/quassel-core","_dir":"apps","_draft":false,"_partial":false,"_locale":"en","id":"quassel-core","name":"quassel-core","icon":"https://raw.githubusercontent.com/walkxcode/dashboard-icons/main/png/quasselcore.png","links":[{"type":"docker","url":"https://hub.docker.com/r/linuxserver/quassel-core"},{"type":"docs","url":"https://docs.linuxserver.io/images/docker-quassel-core"}],"containers":[{"name":"quassel-core","image":"linuxserver/quassel-core","env":[{"id":"PUID","key":"PUID","description":"User ID","default":"100"},{"id":"PGID","key":"PGID","description":"Group ID","default":"100"},{"id":"TZ","key":"TZ","description":"Timezone","default":"America/New_York"}],"volumes":[{"container":"/config","description":"Image exposes volume mounted at /config","key":"config"}],"ports":[{"container":10113,"description":"Image exposes port 10113 over tcp","protocol":"tcp","web":true},{"container":4242,"description":"Image exposes port 4242 over tcp","protocol":"tcp","web":true}]}],"_id":"content:apps:quassel-core.json","_type":"json","title":"Quassel Core","_source":"content","_file":"apps/quassel-core.json","_extension":"json"}