{"_path":"/apps/ubooquity","_dir":"apps","_draft":false,"_partial":false,"_locale":"en","id":"ubooquity","name":"ubooquity","description":"[{{ project_name|capitalize }}]({{ project_url }}) is a free, lightweight and easy-to-use home server for your comics and ebooks. Use it to access your files from anywhere, with a tablet, an e-reader, a phone or a computer.","icon":"https://raw.githubusercontent.com/linuxserver/docker-templates/master/linuxserver.io/img/ubooquity-banner.png","links":[{"type":"docker","url":"https://hub.docker.com/r/linuxserver/ubooquity"},{"type":"docs","url":"https://docs.linuxserver.io/images/docker-ubooquity"}],"containers":[{"name":"ubooquity","image":"linuxserver/ubooquity","env":[{"id":"PUID","key":"PUID","description":"User ID","default":"100"},{"id":"PGID","key":"PGID","description":"Group ID","default":"100"},{"id":"TZ","key":"TZ","description":"Timezone","default":"America/New_York"}],"volumes":[{"container":"/config","description":"Config files and database for ubooquity.","key":"config"},{"container":"/books","description":"Location of books."},{"container":"/comics","description":"Location of comics."},{"container":"/files","description":"Location of raw files."}],"ports":[{"container":"2202","description":"The library port."},{"container":"2203","description":"The admin port."}]}],"_id":"content:apps:ubooquity.json","_type":"json","title":"Ubooquity","_source":"content","_file":"apps/ubooquity.json","_extension":"json"}