{"_path":"/apps/jenkins-builder","_dir":"apps","_draft":false,"_partial":false,"_locale":"en","id":"jenkins-builder","name":"jenkins-builder","icon":"https://raw.githubusercontent.com/walkxcode/dashboard-icons/main/png/jenkinsbuilder.png","links":[{"type":"docker","url":"https://hub.docker.com/r/linuxserver/jenkins-builder"},{"type":"docs","url":"https://docs.linuxserver.io/images/docker-jenkins-builder"}],"containers":[{"name":"jenkins-builder","image":"linuxserver/jenkins-builder","env":[{"id":"PUID","key":"PUID","description":"User ID","default":"100"},{"id":"PGID","key":"PGID","description":"Group ID","default":"100"}]}],"meta":{"readme-vars":{"project_name":"jenkins-builder","full_custom_readme":"{% raw -%}\n# linuxserver/jenkins-builder\n\nExpects to run as part of the LSIO CI process. Not for public consumption.\n\n## Running against remote project\n\n```bash\ndocker run --rm \\\n  -e CONTAINER_NAME=${CONTAINER_NAME} \\\n  -v ${TEMPDIR}:/ansible/jenkins \\\n  lscr.io/linuxserver/jenkins-builder:latest\n```\n\n## Running against local project\n\nIf you need to test functionality just navigate to the folder with the jenkins-vars.yml and run:\n\n```bash\ndocker pull lscr.io/linuxserver/jenkins-builder:latest && \\\ndocker run --rm \\\n  -v $(pwd):/tmp \\\n  -e LOCAL=true \\\n  -e PUID=$(id -u) -e PGID=$(id -g) \\\n  lscr.io/linuxserver/jenkins-builder:latest && \\\nrm -rf .jenkins-external\n```\n\nNewly generated files (including `README.md`, `Jenkinsfile`, issue templates, etc.) will overwrite the existing files in your current working directory.\n\n## Building locally\n\nIf you want to make local modifications to these images for development purposes or just to customize the logic:\n\n```bash\ngit clone https://github.com/linuxserver/docker-jenkins-builder.git\ncd docker-jenkins-builder\ndocker build \\\n  --no-cache \\\n  --pull \\\n  -t lscr.io/linuxserver/jenkins-builder:latest .\n```\n\nThe ARM variants can be built on x86_64 hardware using `multiarch/qemu-user-static`\n\n```bash\ndocker run --rm --privileged multiarch/qemu-user-static:register --reset\n```\n\nOnce registered you can define the dockerfile to use with `-f Dockerfile.aarch64`.\n\n## Versions\n\nThe following line is only in this repo for loop testing:\n\n- { date: \"01.01.50:\", desc: \"I am the release message for this internal repo.\" }\n{%- endraw %}\n"}},"_id":"content:apps:jenkins-builder.json","_type":"json","title":"Jenkins Builder","_source":"content","_file":"apps/jenkins-builder.json","_extension":"json"}