{"_path":"/apps/plex-meta-manager","_dir":"apps","_draft":false,"_partial":false,"_locale":"en","id":"plex-meta-manager","name":"plex-meta-manager","description":"[{{ project_name|capitalize }}]({{ project_url }}) is a Python 3 script that can be continuously run using YAML configuration files to update on a schedule the metadata of the movies, shows, and collections in your libraries as well as automatically build collections based on various methods all detailed in the wiki.","icon":"https://raw.githubusercontent.com/linuxserver/docker-templates/master/linuxserver.io/img/plex-meta-manager-banner.png","links":[{"type":"docker","url":"https://hub.docker.com/r/linuxserver/plex-meta-manager"},{"type":"docs","url":"https://docs.linuxserver.io/images/docker-plex-meta-manager"}],"containers":[{"name":"plex-meta-manager","image":"linuxserver/plex-meta-manager","env":[{"id":"PUID","key":"PUID","description":"User ID","default":"100"},{"id":"PGID","key":"PGID","description":"Group ID","default":"100"},{"id":"TZ","key":"TZ","description":"Timezone","default":"America/New_York"}],"volumes":[{"container":"/config","description":"Local path for plex-meta-manager config files.","key":"config"}]}],"_id":"content:apps:plex-meta-manager.json","_type":"json","title":"Plex Meta Manager","_source":"content","_file":"apps/plex-meta-manager.json","_extension":"json"}